smsframework_clickatell/__init__.py
smsframework_clickatell/api.py
smsframework_clickatell/const.py
smsframework_clickatell/error.py
smsframework_clickatell/provider.py
smsframework_clickatell/receiver.py
smsframework_clickatell/status.py
smsframework_clickatell-0.0.3.post0.dist-info/LICENSE
smsframework_clickatell-0.0.3.post0.dist-info/METADATA
smsframework_clickatell-0.0.3.post0.dist-info/WHEEL
smsframework_clickatell-0.0.3.post0.dist-info/top_level.txt
smsframework_clickatell-0.0.3.post0.dist-info/RECORD
