Metadata-Version: 2.1
Name: smsframework-clickatell
Version: 0.0.3.post0
Summary: SMS framework: Clickatell provider 
Home-page: https://github.com/kolypto/py-smsframework-clickatell
Author: Mark Vartanyan
Author-email: kolypto@gmail.com
License: BSD
Keywords: sms,message,notification,receive,send,clickatell
Platform: any
Classifier: Development Status :: 5 - Production/Stable
Classifier: Intended Audience :: Developers
Classifier: Natural Language :: English
Classifier: Programming Language :: Python :: 2
Classifier: Programming Language :: Python :: 3
Classifier: Operating System :: OS Independent
Requires-Dist: smsframework (>=0.0.9)
Provides-Extra: receiver
Requires-Dist: flask (>=0.10) ; extra == 'receiver'
